docker_swabber/__init__.py
docker_swabber/cli.py
dockerswabber-0.1.1.dist-info/METADATA
dockerswabber-0.1.1.dist-info/WHEEL
dockerswabber-0.1.1.dist-info/entry_points.txt
dockerswabber-0.1.1.dist-info/top_level.txt
dockerswabber-0.1.1.dist-info/RECORD
