Metadata-Version: 2.1
Name: dockerswabber
Version: 0.1.1
Summary: Small CLI to automate management of Docker hub image tags.
Home-page: https://github.com/LongTailBio/python-docker-swabber
Author: Benjamin Chrobot
Author-email: benjamin.blair.chrobot@gmail.com
License: BSD
Platform: any
Classifier: Development Status :: 4 - Beta
Classifier: Environment :: Console
Classifier: Intended Audience :: Developers
Classifier: License :: OSI Approved :: BSD License
Classifier: Operating System :: POSIX
Classifier: Operating System :: MacOS
Classifier: Operating System :: Unix
Classifier: Operating System :: Microsoft :: Windows
Classifier: Programming Language :: Python
Classifier: Programming Language :: Python :: 2
Classifier: Programming Language :: Python :: 3
Classifier: Topic :: Software Development :: Libraries :: Python Modules
Requires-Dist: click
Requires-Dist: semantic-version
